am_random_generator-0.1.1.dist-info/licenses/LICENSE
randomgen/__init__.py
randomgen/generator.py
am_random_generator-0.1.1.dist-info/METADATA
am_random_generator-0.1.1.dist-info/WHEEL
am_random_generator-0.1.1.dist-info/top_level.txt
am_random_generator-0.1.1.dist-info/RECORD
