Metadata-Version: 2.4
Name: am-random-generator
Version: 0.1.1
Summary: A Python package to generate random strings with numbers, characters, or both
Home-page: https://github.com/ashish4824/RandomValue
Author: Ashish
Author-email: ashishmaurya0408@gmail.com
Keywords: random generator string number character
Classifier: Programming Language :: Python :: 3
Classifier: License :: OSI Approved :: MIT License
Classifier: Intended Audience :: Developers
Classifier: Operating System :: OS Independent
Classifier: Topic :: Software Development :: Libraries :: Python Modules
Requires-Python: >=3.6
License-File: LICENSE
Dynamic: author
Dynamic: author-email
Dynamic: classifier
Dynamic: description
Dynamic: description-content-type
Dynamic: home-page
Dynamic: keywords
Dynamic: license-file
Dynamic: requires-python
Dynamic: summary
